libflavour/__init__.py
libflavour/exceptions.py
libflavour/fields/__init__.py
libflavour/fields/base.py
libflavour/fields/scalar.py
libflavour/fields/service.py
libflavour/schema.py
libflavour/test/__init__.py
libflavour/test/data/example_addon.yaml
libflavour/test/data/example_addon_data_1.yaml
libflavour/test/data/example_addon_data_2.yaml
libflavour/test/data/example_addon_data_3.yaml
libflavour/test/data/example_addon_data_4.yaml
libflavour/test/data/example_addon_data_5.yaml
libflavour/test/data/example_addon_dependencies.yaml
libflavour/test/data/example_addon_minimal.yaml
libflavour/test/data/example_addon_minimal_error.yaml
libflavour/test/data/example_aldryn_redirect.yaml
libflavour/test/data/example_project.yaml
libflavour/test/data/example_project_minimal_1.yaml
libflavour/test/data/example_project_minimal_1_error.yaml
libflavour/test/data/example_project_minimal_2.yaml
libflavour/test/data/example_project_minimal_2_error.yaml
libflavour/test/test_entity.py
libflavour/test/test_schema_addon.py
libflavour/test/test_schema_project.py
libflavour/utils.py
libflavour-0.0.19.dist-info/LICENSE
libflavour-0.0.19.dist-info/WHEEL
libflavour-0.0.19.dist-info/METADATA
libflavour-0.0.19.dist-info/RECORD
