Metadata-Version: 2.1
Name: libflavour
Version: 0.0.19
Summary: 
Author: Dennis Schwertel
Author-email: dennisschwertel@gmail.com
Requires-Python: >3.5
Classifier: Programming Language :: Python :: 3
Classifier: Programming Language :: Python :: 3.6
Classifier: Programming Language :: Python :: 3.7
Requires-Dist: attrs
Requires-Dist: python-slugify
Requires-Dist: strictyaml
